README.rst
setup.py
ServiceCreator.egg-info/PKG-INFO
ServiceCreator.egg-info/SOURCES.txt
ServiceCreator.egg-info/dependency_links.txt
ServiceCreator.egg-info/entry_points.txt
ServiceCreator.egg-info/not-zip-safe
ServiceCreator.egg-info/requires.txt
ServiceCreator.egg-info/top_level.txt
service_creator/__init__.py
service_creator/exceptions/__init__.py
service_creator/output/__init__.py
service_creator/utils/__init__.py
service_creator/values/Constants.py
service_creator/values/__init__.py