Metadata-Version: 2.1
Name: ServiceCreator
Version: 1.12
Summary: Create custom services for your Debian-based systems (such as Ubuntu) with this tool | Automate the process and make everything faster and easier than ever
Home-page: https://github.com/Javinator9889/ServiceCreator
Author: Javinator9889
Author-email: javialonso007@hotmail.es
License: GPL-3.0
Download-URL: https://github.com/Javinator9889/ServiceCreator/archive/master.zip
Platform: UNKNOWN
Classifier: Development Status :: 5 - Production/Stable
Classifier: Programming Language :: Python
Classifier: Environment :: Console
Classifier: License :: OSI Approved :: GNU General Public License v3 (GPLv3)
Classifier: Operating System :: POSIX :: Linux
Classifier: Natural Language :: English
Classifier: Programming Language :: Python :: 3
Classifier: Programming Language :: Python :: 3.1
Classifier: Programming Language :: Python :: 3.2
Classifier: Programming Language :: Python :: 3.3
Classifier: Programming Language :: Python :: 3.4
Classifier: Programming Language :: Python :: 3.5
Classifier: Programming Language :: Python :: 3.6
Classifier: Programming Language :: Python :: 3.7
